saltools/__init__.py
saltools/__main__.py
saltools/common.py
saltools/files.py
saltools/logging.py
saltools/misc.py
saltools/web.py
saltools-0.1.0.dist-info/LICENSE
saltools-0.1.0.dist-info/METADATA
saltools-0.1.0.dist-info/WHEEL
saltools-0.1.0.dist-info/top_level.txt
saltools-0.1.0.dist-info/RECORD
