Metadata-Version: 2.1
Name: saltools
Version: 0.1.0
Summary: some usefull code
Home-page: https://github.com/Saledddar/saltools
Author: saledddar
Author-email: saledddar@gmail.com
License: MIT
Keywords: logging exception
Platform: UNKNOWN
Classifier: Development Status :: 4 - Beta
Classifier: Intended Audience :: Developers
Classifier: License :: OSI Approved :: MIT License
Classifier: Operating System :: Microsoft :: Windows
Classifier: Programming Language :: Python
Classifier: Topic :: Software Development :: Libraries
Requires-Dist: lxml
Requires-Dist: requests
